[
	{
		"id":3,
		"Title":"Tutorial",
		"sceneName":"Tutorial",
		"ColourPercentage":0,
		"unlocked":1,
		"Score":0,
		"Time":0,
		"scoreToConquer":1300,
		"conquered": 0,
		"TTTime": 9000
	},
	{
		"id":4,
		"Title":"Level 1",
		"sceneName":"Level1",
		"Score":0,
		"Time":0,
		"TTTime": 9000,
		"scoreToConquer":300,
		"conquered": 0,
		"ColourPercentage":0,
		"unlocked":0
	},
	{
		"id":3,
		"Title":"Level 3",
		"sceneName":"Level3",
		"Score":0,
		"Time":0,
		"TTTime": 9000,
		"scoreToConquer":3000,
		"conquered": 0,
		"ColourPercentage":0,
		"unlocked":0
	},
	{
		"id":4,
		"Title":"Level 4",
		"sceneName":"Level4",
		"Score":0,
		"Time":0,
		"TTTime": 9000,
		"scoreToConquer":3000,
		"conquered": 0,
		"ColourPercentage":0,
		"unlocked":0
	}
]